<?xml version="1.0" encoding="utf-8" ?>
<dwsync>
<file name="bg_general.jpg" local="128258765166892480" remote="128279477400000000" testing="0" />
<file name="bouton_edit.gif" local="128270504292968752" remote="128279477400000000" testing="0" />
<file name="bouton_email.gif" local="128270514673710944" remote="128279477400000000" testing="0" />
<file name="bouton_liste.gif" local="128270512202851568" remote="128279477400000000" testing="0" />
<file name="bg_1.jpg" local="128258788480000000" remote="128279477400000000" testing="0" />
<file name="bouton_delete.gif" local="128270919702827264" remote="128279477400000000" testing="0" />
<file name="bouton_new.gif" local="128271471360000000" remote="128279477400000000" testing="0" />
<file name="bouton_home.gif" local="128278816943881296" remote="128279477400000000" testing="0" />
<file name="bouton_new_lieu.gif" local="128279324052265424" remote="128279477400000000" testing="0" />
<file name="bouton_new_user.gif" local="128279324801542832" remote="128279477400000000" testing="0" />
</dwsync>